{
  "plant": "Kirkwood FNB",
  "last_updated": "2026-03-25 13:39 SAST",
  "date": "2026-03-25",
  "total_kwh": 115.36,
  "last_hour": 12,
  "status": "ok",
  "alerts": {
    "offline": false,
    "pace_low": false,
    "total_low": false
  },
  "thresholds": {
    "expected_daily_kwh": 214.0,
    "low_day_kwh": 36.0,
    "pace_threshold_pct": 0.3,
    "solar_window": {
      "sunrise": 5.92,
      "sunset": 18.08
    }
  },
  "debug": {
    "curve_fraction": 0.628,
    "expected_by_now": 134.3,
    "actual_kwh": 115.36,
    "pace_trigger": 40.3,
    "projected_total": 183.8,
    "low_day_kwh": 36.0,
    "sunrise": 5.92,
    "sunset": 18.08,
    "checks": {
      "pace_low": false,
      "total_low": false
    }
  },
  "hourly_pv": [
    0.0,
    0.0,
    0.0,
    0.0,
    0.0,
    0.0,
    0.3,
    3.57,
    13.05,
    20.3,
    24.86,
    27.04,
    26.24,
    0.0,
    0.0,
    0.0,
    0.0,
    0.0,
    0.0,
    0.0,
    0.0,
    0.0,
    0.0,
    0.0
  ]
}